LICENSE
MANIFEST.in
Makefile
README.rst
VERSION
requirements.txt
setup.cfg
setup.py
test_requirements.txt
bin/charms.reactive
bin/charms.reactive.sh
charms/__init__.py
charms.reactive.egg-info/PKG-INFO
charms.reactive.egg-info/SOURCES.txt
charms.reactive.egg-info/dependency_links.txt
charms.reactive.egg-info/requires.txt
charms.reactive.egg-info/top_level.txt
charms/reactive/__init__.py
charms/reactive/bus.py
charms/reactive/cli.py
charms/reactive/decorators.py
charms/reactive/endpoints.py
charms/reactive/flags.py
charms/reactive/helpers.py
charms/reactive/relations.py
charms/reactive/trace.py
charms/reactive/patterns/request_response.py
scripts/update-revno
tests/test_bus.py
tests/test_decorators.py
tests/test_endpoints.py
tests/test_flags.py
tests/test_helpers.py
tests/test_main.py
tests/test_relations.py
tests/test_request_response.py
tests/test_trace.py