Metadata-Version: 2.1
Name: charms.reactive
Version: 1.5.3
Summary: Framework for writing reactive-style Juju Charms
Home-page: https://github.com/juju-solutions/charms.reactive
Author: Charm Reactive Framework Maintainers
Author-email: juju@lists.ubuntu.com
License: Apache License 2.0
License-File: LICENSE
Requires-Dist: pyaml
Requires-Dist: charmhelpers>=0.5.0
